requiresthat/__init__.py
requiresthat/_exceptions.py
requiresthat/_requires.py
requiresthat/_when.py
requiresthat-2025.7.2.0.dist-info/METADATA
requiresthat-2025.7.2.0.dist-info/WHEEL
requiresthat-2025.7.2.0.dist-info/top_level.txt
requiresthat-2025.7.2.0.dist-info/RECORD
