Metadata-Version: 2.4
Name: requiresthat
Version: 2025.7.2.0
Summary: Support for requirements-assisted development
Author-email: Ann T Ropea <bedhanger@gmx.de>
License-Expression: MIT
Project-URL: Homepage, https://gitlab.com/bedhanger/mwe/-/tree/master/python/requiresthat
